LICENSE.txt
MANIFEST.in
README.rst
setup.cfg
setup.py
DGSD.egg-info/PKG-INFO
DGSD.egg-info/SOURCES.txt
DGSD.egg-info/dependency_links.txt
DGSD.egg-info/requires.txt
DGSD.egg-info/top_level.txt
dgsd/__init__.py
dgsd/main.py