Metadata-Version: 2.1
Name: DGSD
Version: 2.0.0
Summary: DGSD: Distributed Graph Representation via Graph Statistical Properties
Home-page: https://github.com/Anwar-Said/DGSD
Download-URL: https://github.com/Anwar-Said/DGSD/releases/download/v2.0.0/DGSD.tar.gz
Author: Anwar Said
Author-email: anwar.said@itu.edu.pk
License: MIT
Classifier: Development Status :: 3 - Alpha
Classifier: License :: OSI Approved :: MIT License
Classifier: Programming Language :: Python :: 3.8
Classifier: Topic :: Scientific/Engineering :: Mathematics
Classifier: Topic :: Scientific/Engineering :: Artificial Intelligence
License-File: LICENSE.txt
